<?xml version="1.0" encoding="UTF-8"?>
<INVENTORY>
<ITEM>
<ITEMTYPE>P</ITEMTYPE>
<ITEMID>98565</ITEMID>
<COLOR>85</COLOR>
<MAXPRICE>-1.0000</MAXPRICE>
<MINQTY>1</MINQTY>
<CONDITION>X</CONDITION>
<REMARKS/>
<NOTIFY>N</NOTIFY>
</ITEM>
<ITEM>
<ITEMTYPE>P</ITEMTYPE>
<ITEMID>57562</ITEMID>
<COLOR>66</COLOR>
<MAXPRICE>-1.0000</MAXPRICE>
<MINQTY>2</MINQTY>
<CONDITION>X</CONDITION>
<REMARKS/>
<NOTIFY>N</NOTIFY>
</ITEM>
<ITEM>
<ITEMTYPE>P</ITEMTYPE>
<ITEMID>93571</ITEMID>
<COLOR>11</COLOR>
<MAXPRICE>-1.0000</MAXPRICE>
<MINQTY>4</MINQTY>
<CONDITION>X</CONDITION>
<REMARKS/>
<NOTIFY>N</NOTIFY>
</ITEM>
<ITEM>
<ITEMTYPE>P</ITEMTYPE>
<ITEMID>50926</ITEMID>
<COLOR>95</COLOR>
<MAXPRICE>-1.0000</MAXPRICE>
<MINQTY>2</MINQTY>
<CONDITION>X</CONDITION>
<REMARKS/>
<NOTIFY>N</NOTIFY>
</ITEM>
<ITEM>
<ITEMTYPE>P</ITEMTYPE>
<ITEMID>50926</ITEMID>
<COLOR>66</COLOR>
<MAXPRICE>-1.0000</MAXPRICE>
<MINQTY>2</MINQTY>
<CONDITION>X</CONDITION>
<REMARKS/>
<NOTIFY>N</NOTIFY>
</ITEM>
<ITEM>
<ITEMTYPE>P</ITEMTYPE>
<ITEMID>75c03</ITEMID>
<COLOR>10</COLOR>
<MAXPRICE>-1.0000</MAXPRICE>
<MINQTY>2</MINQTY>
<CONDITION>X</CONDITION>
<REMARKS/>
<NOTIFY>N</NOTIFY>
</ITEM>
<ITEM>
<ITEMTYPE>P</ITEMTYPE>
<ITEMID>32489</ITEMID>
<COLOR>11</COLOR>
<MAXPRICE>-1.0000</MAXPRICE>
<MINQTY>1</MINQTY>
<CONDITION>X</CONDITION>
<NOTIFY>N</NOTIFY>
</ITEM>
<ITEM>
<ITEMTYPE>P</ITEMTYPE>
<ITEMID>32506</ITEMID>
<COLOR>66</COLOR>
<MAXPRICE>-1.0000</MAXPRICE>
<MINQTY>1</MINQTY>
<CONDITION>X</CONDITION>
<NOTIFY>N</NOTIFY>
</ITEM>
<ITEM>
<ITEMTYPE>P</ITEMTYPE>
<ITEMID>41668</ITEMID>
<COLOR>11</COLOR>
<MAXPRICE>-1.0000</MAXPRICE>
<MINQTY>1</MINQTY>
<CONDITION>X</CONDITION>
<NOTIFY>N</NOTIFY>
</ITEM>
<ITEM>
<ITEMTYPE>P</ITEMTYPE>
<ITEMID>x1192px1</ITEMID>
<COLOR>11</COLOR>
<MAXPRICE>-1.0000</MAXPRICE>
<MINQTY>6</MINQTY>
<CONDITION>X</CONDITION>
<REMARKS/>
<NOTIFY>N</NOTIFY>
</ITEM>
<ITEM>
<ITEMTYPE>P</ITEMTYPE>
<ITEMID>57571</ITEMID>
<COLOR>66</COLOR>
<MAXPRICE>-1.0000</MAXPRICE>
<MINQTY>5</MINQTY>
<CONDITION>X</CONDITION>
<REMARKS/>
<NOTIFY>N</NOTIFY>
</ITEM>
<ITEM>
<ITEMTYPE>P</ITEMTYPE>
<ITEMID>64276</ITEMID>
<COLOR>85</COLOR>
<MAXPRICE>-1.0000</MAXPRICE>
<MINQTY>4</MINQTY>
<CONDITION>X</CONDITION>
<REMARKS/>
<NOTIFY>N</NOTIFY>
</ITEM>
<ITEM>
<ITEMTYPE>P</ITEMTYPE>
<ITEMID>22961</ITEMID>
<COLOR>85</COLOR>
<MAXPRICE>-1.0000</MAXPRICE>
<MINQTY>4</MINQTY>
<CONDITION>X</CONDITION>
<REMARKS/>
<NOTIFY>N</NOTIFY>
</ITEM>
<ITEM>
<ITEMTYPE>P</ITEMTYPE>
<ITEMID>53566</ITEMID>
<COLOR>66</COLOR>
<MAXPRICE>-1.0000</MAXPRICE>
<MINQTY>4</MINQTY>
<CONDITION>X</CONDITION>
<REMARKS/>
<NOTIFY>N</NOTIFY>
</ITEM>
<ITEM>
<ITEMTYPE>P</ITEMTYPE>
<ITEMID>10197</ITEMID>
<COLOR>85</COLOR>
<MAXPRICE>-1.0000</MAXPRICE>
<MINQTY>4</MINQTY>
<CONDITION>X</CONDITION>
<NOTIFY>N</NOTIFY>
</ITEM>
<ITEM>
<ITEMTYPE>P</ITEMTYPE>
<ITEMID>18654</ITEMID>
<COLOR>85</COLOR>
<MAXPRICE>-1.0000</MAXPRICE>
<MINQTY>2</MINQTY>
<CONDITION>X</CONDITION>
<NOTIFY>N</NOTIFY>
</ITEM>
<ITEM>
<ITEMTYPE>P</ITEMTYPE>
<ITEMID>32200</ITEMID>
<COLOR>95</COLOR>
<MAXPRICE>-1.0000</MAXPRICE>
<MINQTY>4</MINQTY>
<CONDITION>X</CONDITION>
<NOTIFY>N</NOTIFY>
</ITEM>
<ITEM>
<ITEMTYPE>P</ITEMTYPE>
<ITEMID>32202</ITEMID>
<COLOR>66</COLOR>
<MAXPRICE>-1.0000</MAXPRICE>
<MINQTY>4</MINQTY>
<CONDITION>X</CONDITION>
<NOTIFY>N</NOTIFY>
</ITEM>
<ITEM>
<ITEMTYPE>P</ITEMTYPE>
<ITEMID>32235</ITEMID>
<COLOR>66</COLOR>
<MAXPRICE>-1.0000</MAXPRICE>
<MINQTY>4</MINQTY>
<CONDITION>X</CONDITION>
<NOTIFY>N</NOTIFY>
</ITEM>
<ITEM>
<ITEMTYPE>P</ITEMTYPE>
<ITEMID>32310</ITEMID>
<COLOR>66</COLOR>
<MAXPRICE>-1.0000</MAXPRICE>
<MINQTY>4</MINQTY>
<CONDITION>X</CONDITION>
<NOTIFY>N</NOTIFY>
</ITEM>
<ITEM>
<ITEMTYPE>P</ITEMTYPE>
<ITEMID>32348</ITEMID>
<COLOR>11</COLOR>
<MAXPRICE>-1.0000</MAXPRICE>
<MINQTY>3</MINQTY>
<CONDITION>X</CONDITION>
<NOTIFY>N</NOTIFY>
</ITEM>
<ITEM>
<ITEMTYPE>P</ITEMTYPE>
<ITEMID>43558</ITEMID>
<COLOR>66</COLOR>
<MAXPRICE>-1.0000</MAXPRICE>
<MINQTY>1</MINQTY>
<CONDITION>X</CONDITION>
<NOTIFY>N</NOTIFY>
</ITEM>
<ITEM>
<ITEMTYPE>P</ITEMTYPE>
<ITEMID>44140</ITEMID>
<COLOR>66</COLOR>
<MAXPRICE>-1.0000</MAXPRICE>
<MINQTY>3</MINQTY>
<CONDITION>X</CONDITION>
<NOTIFY>N</NOTIFY>
</ITEM>
<ITEM>
<ITEMTYPE>P</ITEMTYPE>
<ITEMID>44139</ITEMID>
<COLOR>5</COLOR>
<MAXPRICE>-1.0000</MAXPRICE>
<MINQTY>1</MINQTY>
<CONDITION>X</CONDITION>
<NOTIFY>N</NOTIFY>
</ITEM>
<ITEM>
<ITEMTYPE>P</ITEMTYPE>
<ITEMID>44142</ITEMID>
<COLOR>66</COLOR>
<MAXPRICE>-1.0000</MAXPRICE>
<MINQTY>1</MINQTY>
<CONDITION>X</CONDITION>
<NOTIFY>N</NOTIFY>
</ITEM>
<ITEM>
<ITEMTYPE>P</ITEMTYPE>
<ITEMID>47337</ITEMID>
<COLOR>66</COLOR>
<MAXPRICE>-1.0000</MAXPRICE>
<MINQTY>1</MINQTY>
<CONDITION>X</CONDITION>
<NOTIFY>N</NOTIFY>
</ITEM>
<ITEM>
<ITEMTYPE>P</ITEMTYPE>
<ITEMID>50923</ITEMID>
<COLOR>85</COLOR>
<MAXPRICE>-1.0000</MAXPRICE>
<MINQTY>2</MINQTY>
<CONDITION>X</CONDITION>
<NOTIFY>N</NOTIFY>
</ITEM>
<ITEM>
<ITEMTYPE>P</ITEMTYPE>
<ITEMID>60483</ITEMID>
<COLOR>85</COLOR>
<MAXPRICE>-1.0000</MAXPRICE>
<MINQTY>2</MINQTY>
<CONDITION>X</CONDITION>
<NOTIFY>N</NOTIFY>
</ITEM>
<ITEM>
<ITEMTYPE>P</ITEMTYPE>
<ITEMID>90612</ITEMID>
<COLOR>11</COLOR>
<MAXPRICE>-1.0000</MAXPRICE>
<MINQTY>2</MINQTY>
<CONDITION>X</CONDITION>
<NOTIFY>N</NOTIFY>
</ITEM>
<ITEM>
<ITEMTYPE>P</ITEMTYPE>
<ITEMID>89678</ITEMID>
<COLOR>5</COLOR>
<MAXPRICE>-1.0000</MAXPRICE>
<MINQTY>2</MINQTY>
<CONDITION>X</CONDITION>
<NOTIFY>N</NOTIFY>
</ITEM>
<ITEM>
<ITEMTYPE>P</ITEMTYPE>
<ITEMID>15100</ITEMID>
<COLOR>86</COLOR>
<MAXPRICE>-1.0000</MAXPRICE>
<MINQTY>6</MINQTY>
<CONDITION>X</CONDITION>
<NOTIFY>N</NOTIFY>
</ITEM>
<ITEM>
<ITEMTYPE>P</ITEMTYPE>
<ITEMID>32201</ITEMID>
<COLOR>66</COLOR>
<MAXPRICE>-1.0000</MAXPRICE>
<MINQTY>6</MINQTY>
<CONDITION>X</CONDITION>
<NOTIFY>N</NOTIFY>
</ITEM>
<ITEM>
<ITEMTYPE>P</ITEMTYPE>
<ITEMID>32474</ITEMID>
<COLOR>11</COLOR>
<MAXPRICE>-1.0000</MAXPRICE>
<MINQTY>17</MINQTY>
<CONDITION>X</CONDITION>
<NOTIFY>N</NOTIFY>
</ITEM>
<ITEM>
<ITEMTYPE>P</ITEMTYPE>
<ITEMID>41672</ITEMID>
<COLOR>11</COLOR>
<MAXPRICE>-1.0000</MAXPRICE>
<MINQTY>6</MINQTY>
<CONDITION>X</CONDITION>
<NOTIFY>N</NOTIFY>
</ITEM>
<ITEM>
<ITEMTYPE>P</ITEMTYPE>
<ITEMID>42003</ITEMID>
<COLOR>86</COLOR>
<MAXPRICE>-1.0000</MAXPRICE>
<MINQTY>4</MINQTY>
<CONDITION>X</CONDITION>
<NOTIFY>N</NOTIFY>
</ITEM>
<ITEM>
<ITEMTYPE>P</ITEMTYPE>
<ITEMID>6632</ITEMID>
<COLOR>85</COLOR>
<MAXPRICE>-1.0000</MAXPRICE>
<MINQTY>22</MINQTY>
<CONDITION>X</CONDITION>
<NOTIFY>N</NOTIFY>
</ITEM>
<ITEM>
<ITEMTYPE>P</ITEMTYPE>
<ITEMID>44136</ITEMID>
<COLOR>10</COLOR>
<MAXPRICE>-1.0000</MAXPRICE>
<MINQTY>5</MINQTY>
<CONDITION>X</CONDITION>
<NOTIFY>N</NOTIFY>
</ITEM>
<ITEM>
<ITEMTYPE>P</ITEMTYPE>
<ITEMID>45749</ITEMID>
<COLOR>66</COLOR>
<MAXPRICE>-1.0000</MAXPRICE>
<MINQTY>4</MINQTY>
<CONDITION>X</CONDITION>
<NOTIFY>N</NOTIFY>
</ITEM>
<ITEM>
<ITEMTYPE>P</ITEMTYPE>
<ITEMID>50858</ITEMID>
<COLOR>66</COLOR>
<MAXPRICE>-1.0000</MAXPRICE>
<MINQTY>4</MINQTY>
<CONDITION>X</CONDITION>
<NOTIFY>N</NOTIFY>
</ITEM>
<ITEM>
<ITEMTYPE>P</ITEMTYPE>
<ITEMID>53586</ITEMID>
<COLOR>66</COLOR>
<MAXPRICE>-1.0000</MAXPRICE>
<MINQTY>6</MINQTY>
<CONDITION>X</CONDITION>
<NOTIFY>N</NOTIFY>
</ITEM>
<ITEM>
<ITEMTYPE>P</ITEMTYPE>
<ITEMID>92907</ITEMID>
<COLOR>86</COLOR>
<MAXPRICE>-1.0000</MAXPRICE>
<MINQTY>6</MINQTY>
<CONDITION>X</CONDITION>
<NOTIFY>N</NOTIFY>
</ITEM>
<ITEM>
<ITEMTYPE>P</ITEMTYPE>
<ITEMID>93571</ITEMID>
<COLOR>85</COLOR>
<MAXPRICE>-1.0000</MAXPRICE>
<MINQTY>14</MINQTY>
<CONDITION>X</CONDITION>
<NOTIFY>N</NOTIFY>
</ITEM>
<ITEM>
<ITEMTYPE>P</ITEMTYPE>
<ITEMID>57539</ITEMID>
<COLOR>95</COLOR>
<MAXPRICE>-1.0000</MAXPRICE>
<MINQTY>4</MINQTY>
<CONDITION>X</CONDITION>
<NOTIFY>N</NOTIFY>
</ITEM>
<ITEM>
<ITEMTYPE>P</ITEMTYPE>
<ITEMID>14301</ITEMID>
<COLOR>86</COLOR>
<MAXPRICE>-1.0000</MAXPRICE>
<MINQTY>4</MINQTY>
<CONDITION>X</CONDITION>
<NOTIFY>N</NOTIFY>
</ITEM>
</INVENTORY>
